permutationimportancephysics/PermutationImportance.py
permutationimportancephysics/__init__.py
PermutationImportancePhysics-0.111.dist-info/LICENSE.txt
PermutationImportancePhysics-0.111.dist-info/METADATA
PermutationImportancePhysics-0.111.dist-info/WHEEL
PermutationImportancePhysics-0.111.dist-info/top_level.txt
PermutationImportancePhysics-0.111.dist-info/RECORD
