Metadata-Version: 2.1
Name: PermutationImportancePhysics
Version: 0.111
Summary: Permutation Importance for Physics
Home-page: https://github.com/aghoshpub/permutationImportancePhysics
Author: A Ghosh
License: UNKNOWN
Platform: UNKNOWN
